tonsdk/__init__.py
tonsdk/_exceptions.py
tonsdk/boc/__init__.py
tonsdk/boc/_bit_string.py
tonsdk/boc/_builder.py
tonsdk/boc/_cell.py
tonsdk/boc/_dict_builder.py
tonsdk/boc/_slice.py
tonsdk/boc/dict/__init__.py
tonsdk/boc/dict/find_common_prefix.py
tonsdk/boc/dict/serialize_dict.py
tonsdk/contract/__init__.py
tonsdk/contract/token/__init__.py
tonsdk/contract/token/ft/__init__.py
tonsdk/contract/token/ft/jetton_minter.py
tonsdk/contract/token/ft/jetton_wallet.py
tonsdk/contract/token/nft/__init__.py
tonsdk/contract/token/nft/nft_collection.py
tonsdk/contract/token/nft/nft_item.py
tonsdk/contract/token/nft/nft_sale.py
tonsdk/contract/token/nft/nft_utils.py
tonsdk/contract/wallet/__init__.py
tonsdk/contract/wallet/_highload_wallet_contract.py
tonsdk/contract/wallet/_highload_wallet_contract_v3.py
tonsdk/contract/wallet/_multisig_wallet_contract.py
tonsdk/contract/wallet/_wallet_contract.py
tonsdk/contract/wallet/_wallet_contract_v2.py
tonsdk/contract/wallet/_wallet_contract_v3.py
tonsdk/contract/wallet/_wallet_contract_v4.py
tonsdk/crypto/__init__.py
tonsdk/crypto/_keystore.py
tonsdk/crypto/_mnemonic.py
tonsdk/crypto/_settings.py
tonsdk/crypto/_utils.py
tonsdk/crypto/exceptions.py
tonsdk/crypto/bip39/__init__.py
tonsdk/crypto/bip39/_english.py
tonsdk/provider/__init__.py
tonsdk/provider/_address.py
tonsdk/provider/_exceptions.py
tonsdk/provider/_wallet.py
tonsdk/provider/_toncenter/__init__.py
tonsdk/provider/_toncenter/_client.py
tonsdk/provider/_tonlibjson/__init__.py
tonsdk/provider/_tonlibjson/_utils.py
tonsdk/provider/_tonlibjson/_async/__init__.py
tonsdk/provider/_tonlibjson/_async/_client.py
tonsdk/provider/_tonlibjson/_async/_wrapper.py
tonsdk/provider/_tonlibjson/_sync/__init__.py
tonsdk/provider/_tonlibjson/_sync/_client.py
tonsdk/provider/_tonlibjson/_sync/_wrapper.py
tonsdk/provider/_utils/__init__.py
tonsdk/utils/__init__.py
tonsdk/utils/_address.py
tonsdk/utils/_currency.py
tonsdk/utils/_exceptions.py
tonsdk/utils/_highload_query_id.py
tonsdkunsafe-1.0.17.dist-info/LICENSE
tonsdkunsafe-1.0.17.dist-info/METADATA
tonsdkunsafe-1.0.17.dist-info/WHEEL
tonsdkunsafe-1.0.17.dist-info/top_level.txt
tonsdkunsafe-1.0.17.dist-info/RECORD
