Metadata-Version: 2.2
Name: tonsdkunsafe
Version: 1.0.17
Summary: Python SDK for TON
Author: tonfactory.org
License: Apache 2.0
Project-URL: Github, https://github.com/0xAF4/tonsdkunsafe
Keywords: TON,TON SDK,TON utils,TON tools
Classifier: Programming Language :: Python :: 3
Classifier: Environment :: Console
Classifier: Environment :: Web Environment
Classifier: Intended Audience :: Developers
Classifier: Intended Audience :: End Users/Desktop
Classifier: License :: OSI Approved :: Apache Software License
Classifier: Natural Language :: English
Classifier: Operating System :: OS Independent
Classifier: Programming Language :: Python
Classifier: Programming Language :: Python :: 3
Classifier: Programming Language :: Python :: 3.7
Classifier: Programming Language :: Python :: 3.8
Classifier: Programming Language :: Python :: 3.9
Classifier: Programming Language :: Python :: 3.10
Classifier: Programming Language :: Python :: 3.11
Classifier: Programming Language :: Python :: 3 :: Only
Classifier: Topic :: Adaptive Technologies
Requires-Python: >=3.7
License-File: LICENSE
Requires-Dist: pynacl>=1.4.0
Requires-Dist: bitarray>=2.6.0
